README.rst
setup.py
sslscan/__about__.py
sslscan/__init__.py
sslscan/config.py
sslscan/exception.py
sslscan/kb.py
sslscan/ui.py
sslscan.egg-info/PKG-INFO
sslscan.egg-info/SOURCES.txt
sslscan.egg-info/dependency_links.txt
sslscan.egg-info/entry_points.txt
sslscan.egg-info/not-zip-safe
sslscan.egg-info/requires.txt
sslscan.egg-info/top_level.txt
sslscan/_helper/__init__.py
sslscan/_helper/int_ssl.py
sslscan/_helper/openssl.py
sslscan/module/__init__.py
sslscan/module/handler/__init__.py
sslscan/module/handler/http.py
sslscan/module/handler/imap.py
sslscan/module/handler/ldap.py
sslscan/module/handler/pop3.py
sslscan/module/handler/rdp.py
sslscan/module/handler/smtp.py
sslscan/module/handler/tcp.py
sslscan/module/handler/udp.py
sslscan/module/rating/__init__.py
sslscan/module/rating/builtin.py
sslscan/module/rating/none.py
sslscan/module/rating/rbsec.py
sslscan/module/rating/ssllabs.py
sslscan/module/report/__init__.py
sslscan/module/report/terminal.py
sslscan/module/scan/__init__.py
sslscan/module/scan/client_ciphers.py
sslscan/module/scan/protocol_http.py
sslscan/module/scan/protocol_imap.py
sslscan/module/scan/protocol_pop3.py
sslscan/module/scan/protocol_smtp.py
sslscan/module/scan/server_certificate.py
sslscan/module/scan/server_ciphers.py
sslscan/module/scan/server_compression.py
sslscan/module/scan/server_elliptic_curves.py
sslscan/module/scan/server_preferred_ciphers.py
sslscan/module/scan/server_renegotiation.py
sslscan/module/scan/server_scsv.py
sslscan/module/scan/vuln_heartbleed.py