Metadata-Version: 1.1
Name: sslscan
Version: 0.5
Summary: Framework and command-line tool to scan SSL enabled services
Home-page: https://github.com/DinoTools/pysslscan
Author: PhiBo (DinoTools)
Author-email: UNKNOWN
License: LGPLv3+
Platform: UNKNOWN
Classifier: Development Status :: 4 - Beta
Classifier: License :: OSI Approved :: GNU Lesser General Public License v3 or later (LGPLv3+)
Classifier: Operating System :: OS Independent
Classifier: Programming Language :: Python
Classifier: Programming Language :: Python :: 2
Classifier: Programming Language :: Python :: 2.7
Classifier: Programming Language :: Python :: 3
Classifier: Programming Language :: Python :: 3.2
Classifier: Programming Language :: Python :: 3.3
Classifier: Programming Language :: Python :: 3.4
